libs/__init__.py
libs/constants.py
dekorl-1.0.2.dist-info/METADATA
dekorl-1.0.2.dist-info/WHEEL
dekorl-1.0.2.dist-info/entry_points.txt
dekorl-1.0.2.dist-info/top_level.txt
dekorl-1.0.2.dist-info/RECORD
