Metadata-Version: 2.4
Name: dekoRL
Version: 1.0.2
Author: MurilooPrDev
Requires-Dist: colorama
Requires-Dist: requests
Dynamic: author
Dynamic: requires-dist
